lib_1/__init__.py
lib_1/models.py
lib_aao_1-0.1.0.dist-info/WHEEL
lib_aao_1-0.1.0.dist-info/METADATA
lib_aao_1-0.1.0.dist-info/RECORD
