Metadata-Version: 2.1
Name: lib-aao-1
Version: 0.1.0
Summary: Tesdt Reposıtory
License: MIT
Keywords: test
Author: Arda Orhan
Author-email: arda.orhan@sennder.com
Requires-Python: >=3.7,<4.0
Classifier: License :: OSI Approved :: MIT License
Classifier: Programming Language :: Python :: 3
Classifier: Programming Language :: Python :: 3.7
Classifier: Programming Language :: Python :: 3.8
Classifier: Programming Language :: Python :: 3.9
Classifier: Programming Language :: Python :: 3.10
Requires-Dist: pydantic (>=1.10.2,<2.0.0)
